winzy_screencapture/__init__.py
winzy_screencapture-0.1.dist-info/LICENSE
winzy_screencapture-0.1.dist-info/METADATA
winzy_screencapture-0.1.dist-info/WHEEL
winzy_screencapture-0.1.dist-info/entry_points.txt
winzy_screencapture-0.1.dist-info/top_level.txt
winzy_screencapture-0.1.dist-info/RECORD
