Metadata-Version: 2.1
Name: winzy-screencapture
Version: 0.1
Summary: Capture screen using imageio
Author: Sukhbinder Singh
License: Apache-2.0
Project-URL: Homepage, https://github.com/sukhbinder/winzy-screencapture
Project-URL: Changelog, https://github.com/sukhbinder/winzy-screencapture/releases
Project-URL: Issues, https://github.com/sukhbinder/winzy-screencapture/issues
Project-URL: CI, https://github.com/sukhbinder/winzy-screencapture/actions
Classifier: License :: OSI Approved :: Apache Software License
License-File: LICENSE
Requires-Dist: winzy
Requires-Dist: imageio
Provides-Extra: test
Requires-Dist: pytest ; extra == 'test'
